crm/__init__.py
crm-0.0.0.dist-info/METADATA
crm-0.0.0.dist-info/RECORD
crm-0.0.0.dist-info/WHEEL
crm-0.0.0.dist-info/top_level.txt
