Metadata-Version: 2.1
Name: crm
Version: 0.0.0
Summary: Eraple CRM (Customer Relationship Management)
Home-page: https://www.eraple.com/
Author: Eraple
Author-email: care@eraple.com
License: UNKNOWN
Platform: UNKNOWN
Classifier: Programming Language :: Python :: 3
Classifier: License :: OSI Approved :: MIT License
Classifier: Operating System :: OS Independent
